{"cameraMode":{"drawMode":0,"name":"Shaded","section":"Shading Mode"},"sceneLighting":true,"audioPlay":false,"sceneViewState":{"m_AlwaysRefresh":false,"showFog":true,"showSkybox":true,"showFlares":true,"showImageEffects":true,"showParticleSystems":true,"showVisualEffectGraphs":true,"m_FxEnabled":true},"in2DMode":false,"pivot":{"x":16.53923797607422,"y":-1.332983374595642,"z":7.652397632598877},"rotation":{"x":0.08195233345031738,"y":0.8275933265686035,"z":-0.12533360719680787,"w":0.5410360097885132},"size":8.010693550109864,"orthographic":false}